<?xml version="1.0"?>
<EmbeddedProfile xmlns:xsi="http://www.w3.org/2001/XMLSchema-instance" xmlns:xsd="http://www.w3.org/2001/XMLSchema">
  <ToolchainID>com.visualgdb.arm-eabi</ToolchainID>
  <ToolchainVersion>
    <GCC>9.2.1</GCC>
    <GDB>8.3.0</GDB>
    <Revision>1</Revision>
  </ToolchainVersion>
  <BspID>com.sysprogs.arm.stm32</BspID>
  <BspVersion>2019.06</BspVersion>
  <McuID>STM32F469NI</McuID>
  <MCUDefinitionFile>STM32F4xxxx/DeviceDefinitions/stm32f469xx.xml</MCUDefinitionFile>
  <MCUProperties>
    <Entries>
      <KeyValue>
        <Key>com.sysprogs.bspoptions.primary_memory</Key>
        <Value>flash</Value>
      </KeyValue>
      <KeyValue>
        <Key>com.sysprogs.bspoptions.arm.floatmode</Key>
        <Value>-mfloat-abi=hard</Value>
      </KeyValue>
      <KeyValue>
        <Key>com.sysprogs.mcuoptions.ignore_startup_file</Key>
      </KeyValue>
      <KeyValue>
        <Key>com.sysprogs.toolchainoptions.arm.libctype</Key>
        <Value>--specs=nano.specs</Value>
      </KeyValue>
      <KeyValue>
        <Key>com.sysprogs.toolchainoptions.arm.syscallspecs</Key>
        <Value>--specs=nosys.specs</Value>
      </KeyValue>
    </Entries>
  </MCUProperties>
  <BSPSourceFolderName>Device-specific files</BSPSourceFolderName>
  <MCUMakFile>stm32.mak</MCUMakFile>
  <ReferencedFrameworks />
  <FrameworkProperties>
    <Entries />
  </FrameworkProperties>
  <TestFrameworkProperties>
    <Entries />
  </TestFrameworkProperties>
  <ImportedProject>
    <ImporterID>com.sysprogs.project_importers.stm32.ide</ImporterID>
    <RelativeProjectPath>..\TouchGFX\STM32CubeIDE\.cproject</RelativeProjectPath>
    <AllDependencies>
      <ProjectDependency>
        <RelativePath>..\TouchGFX\STM32CubeIDE\.cproject</RelativePath>
        <Timestamp>132335451435961393</Timestamp>
      </ProjectDependency>
    </AllDependencies>
    <RootDirectory>
      <Subdirectories>
        <VirtualDirectorySnapshot>
          <Name>Application</Name>
          <Subdirectories>
            <VirtualDirectorySnapshot>
              <Name>User</Name>
              <Subdirectories>
                <VirtualDirectorySnapshot>
                  <Name>generated</Name>
                  <Files>
                    <VirtualFileSnapshot>
                      <RelativePath>..\TouchGFX\TouchGFX\generated\fonts\src\ApplicationFontProvider.cpp</RelativePath>
                    </VirtualFileSnapshot>
                    <VirtualFileSnapshot>
                      <RelativePath>..\TouchGFX\TouchGFX\generated\images\src\BitmapDatabase.cpp</RelativePath>
                    </VirtualFileSnapshot>
                    <VirtualFileSnapshot>
                      <RelativePath>..\TouchGFX\TouchGFX\generated\fonts\src\CachedFont.cpp</RelativePath>
                    </VirtualFileSnapshot>
                    <VirtualFileSnapshot>
                      <RelativePath>..\TouchGFX\TouchGFX\generated\fonts\src\FontCache.cpp</RelativePath>
                    </VirtualFileSnapshot>
                    <VirtualFileSnapshot>
                      <RelativePath>..\TouchGFX\TouchGFX\generated\fonts\src\Font_Asap_Regular_80_4bpp_0.cpp</RelativePath>
                    </VirtualFileSnapshot>
                    <VirtualFileSnapshot>
                      <RelativePath>..\TouchGFX\TouchGFX\generated\gui_generated\src\common\FrontendApplicationBase.cpp</RelativePath>
                    </VirtualFileSnapshot>
                    <VirtualFileSnapshot>
                      <RelativePath>..\TouchGFX\TouchGFX\generated\fonts\src\GeneratedFont.cpp</RelativePath>
                    </VirtualFileSnapshot>
                    <VirtualFileSnapshot>
                      <RelativePath>..\TouchGFX\TouchGFX\generated\fonts\src\Kerning_Asap_Regular_80_4bpp.cpp</RelativePath>
                    </VirtualFileSnapshot>
                    <VirtualFileSnapshot>
                      <RelativePath>..\TouchGFX\TouchGFX\generated\texts\src\LanguageGb.cpp</RelativePath>
                    </VirtualFileSnapshot>
                    <VirtualFileSnapshot>
                      <RelativePath>..\TouchGFX\TouchGFX\generated\gui_generated\src\main_screen\MainViewBase.cpp</RelativePath>
                    </VirtualFileSnapshot>
                    <VirtualFileSnapshot>
                      <RelativePath>..\TouchGFX\TouchGFX\generated\fonts\src\Table_Asap_Regular_80_4bpp.cpp</RelativePath>
                    </VirtualFileSnapshot>
                    <VirtualFileSnapshot>
                      <RelativePath>..\TouchGFX\TouchGFX\generated\texts\src\Texts.cpp</RelativePath>
                    </VirtualFileSnapshot>
                    <VirtualFileSnapshot>
                      <RelativePath>..\TouchGFX\TouchGFX\generated\texts\src\TypedTextDatabase.cpp</RelativePath>
                    </VirtualFileSnapshot>
                    <VirtualFileSnapshot>
                      <RelativePath>..\TouchGFX\TouchGFX\generated\images\src\bg.cpp</RelativePath>
                    </VirtualFileSnapshot>
                    <VirtualFileSnapshot>
                      <RelativePath>..\TouchGFX\TouchGFX\generated\images\src\counter_box.cpp</RelativePath>
                    </VirtualFileSnapshot>
                    <VirtualFileSnapshot>
                      <RelativePath>..\TouchGFX\TouchGFX\generated\images\src\down_btn.cpp</RelativePath>
                    </VirtualFileSnapshot>
                    <VirtualFileSnapshot>
                      <RelativePath>..\TouchGFX\TouchGFX\generated\images\src\down_btn_disabled.cpp</RelativePath>
                    </VirtualFileSnapshot>
                    <VirtualFileSnapshot>
                      <RelativePath>..\TouchGFX\TouchGFX\generated\images\src\down_btn_pressed.cpp</RelativePath>
                    </VirtualFileSnapshot>
                    <VirtualFileSnapshot>
                      <RelativePath>..\TouchGFX\TouchGFX\generated\images\src\up_btn.cpp</RelativePath>
                    </VirtualFileSnapshot>
                    <VirtualFileSnapshot>
                      <RelativePath>..\TouchGFX\TouchGFX\generated\images\src\up_btn_disabled.cpp</RelativePath>
                    </VirtualFileSnapshot>
                    <VirtualFileSnapshot>
                      <RelativePath>..\TouchGFX\TouchGFX\generated\images\src\up_btn_pressed.cpp</RelativePath>
                    </VirtualFileSnapshot>
                  </Files>
                </VirtualDirectorySnapshot>
                <VirtualDirectorySnapshot>
                  <Name>gui</Name>
                  <Files>
                    <VirtualFileSnapshot>
                      <RelativePath>..\TouchGFX\TouchGFX\gui\src\common\FrontendApplication.cpp</RelativePath>
                    </VirtualFileSnapshot>
                    <VirtualFileSnapshot>
                      <RelativePath>..\TouchGFX\TouchGFX\gui\src\main_screen\MainPresenter.cpp</RelativePath>
                    </VirtualFileSnapshot>
                    <VirtualFileSnapshot>
                      <RelativePath>..\TouchGFX\TouchGFX\gui\src\main_screen\MainView.cpp</RelativePath>
                    </VirtualFileSnapshot>
                    <VirtualFileSnapshot>
                      <RelativePath>..\TouchGFX\TouchGFX\gui\src\model\Model.cpp</RelativePath>
                    </VirtualFileSnapshot>
                  </Files>
                </VirtualDirectorySnapshot>
                <VirtualDirectorySnapshot>
                  <Name>TouchGFX</Name>
                  <Subdirectories>
                    <VirtualDirectorySnapshot>
                      <Name>App</Name>
                      <Files>
                        <VirtualFileSnapshot>
                          <RelativePath>..\TouchGFX\TouchGFX\App\app_touchgfx.c</RelativePath>
                        </VirtualFileSnapshot>
                      </Files>
                    </VirtualDirectorySnapshot>
                    <VirtualDirectorySnapshot>
                      <Name>target</Name>
                      <Subdirectories>
                        <VirtualDirectorySnapshot>
                          <Name>generated</Name>
                          <Files>
                            <VirtualFileSnapshot>
                              <RelativePath>..\TouchGFX\TouchGFX\target\generated\OSWrappers.cpp</RelativePath>
                            </VirtualFileSnapshot>
                            <VirtualFileSnapshot>
                              <RelativePath>..\TouchGFX\TouchGFX\target\generated\STM32DMA.cpp</RelativePath>
                            </VirtualFileSnapshot>
                            <VirtualFileSnapshot>
                              <RelativePath>..\TouchGFX\TouchGFX\target\generated\TouchGFXConfiguration.cpp</RelativePath>
                            </VirtualFileSnapshot>
                            <VirtualFileSnapshot>
                              <RelativePath>..\TouchGFX\TouchGFX\target\generated\TouchGFXGeneratedHAL.cpp</RelativePath>
                            </VirtualFileSnapshot>
                          </Files>
                        </VirtualDirectorySnapshot>
                      </Subdirectories>
                      <Files>
                        <VirtualFileSnapshot>
                          <RelativePath>..\TouchGFX\TouchGFX\target\Buttons.cpp</RelativePath>
                        </VirtualFileSnapshot>
                        <VirtualFileSnapshot>
                          <RelativePath>..\TouchGFX\TouchGFX\target\CortexMMCUInstrumentation.cpp</RelativePath>
                        </VirtualFileSnapshot>
                        <VirtualFileSnapshot>
                          <RelativePath>..\TouchGFX\TouchGFX\target\KeySampler.cpp</RelativePath>
                        </VirtualFileSnapshot>
                        <VirtualFileSnapshot>
                          <RelativePath>..\TouchGFX\TouchGFX\target\STM32TouchController.cpp</RelativePath>
                        </VirtualFileSnapshot>
                        <VirtualFileSnapshot>
                          <RelativePath>..\TouchGFX\TouchGFX\target\TouchGFXGPIO.cpp</RelativePath>
                        </VirtualFileSnapshot>
                        <VirtualFileSnapshot>
                          <RelativePath>..\TouchGFX\TouchGFX\target\TouchGFXHAL.cpp</RelativePath>
                        </VirtualFileSnapshot>
                      </Files>
                    </VirtualDirectorySnapshot>
                  </Subdirectories>
                  <Files />
                </VirtualDirectorySnapshot>
              </Subdirectories>
              <Files>
                <VirtualFileSnapshot>
                  <RelativePath>..\TouchGFX\Core\Src\freertos.c</RelativePath>
                </VirtualFileSnapshot>
                <VirtualFileSnapshot>
                  <RelativePath>..\TouchGFX\Core\Src\main.c</RelativePath>
                </VirtualFileSnapshot>
                <VirtualFileSnapshot>
                  <RelativePath>..\TouchGFX\Core\Src\stm32f4xx_hal_msp.c</RelativePath>
                </VirtualFileSnapshot>
                <VirtualFileSnapshot>
                  <RelativePath>..\TouchGFX\Core\Src\stm32f4xx_hal_timebase_tim.c</RelativePath>
                </VirtualFileSnapshot>
                <VirtualFileSnapshot>
                  <RelativePath>..\TouchGFX\Core\Src\stm32f4xx_it.c</RelativePath>
                </VirtualFileSnapshot>
              </Files>
            </VirtualDirectorySnapshot>
          </Subdirectories>
          <Files />
        </VirtualDirectorySnapshot>
        <VirtualDirectorySnapshot>
          <Name>Drivers</Name>
          <Subdirectories>
            <VirtualDirectorySnapshot>
              <Name>CMSIS</Name>
              <Files>
                <VirtualFileSnapshot>
                  <RelativePath>..\TouchGFX\Core\Src\system_stm32f4xx.c</RelativePath>
                </VirtualFileSnapshot>
                <VirtualFileSnapshot>
                  <RelativePath>..\TouchGFX\Core\Inc\FreeRTOSConfig.h</RelativePath>
                </VirtualFileSnapshot>
                <VirtualFileSnapshot>
                  <RelativePath>..\TouchGFX\Core\Inc\main.h</RelativePath>
                </VirtualFileSnapshot>
                <VirtualFileSnapshot>
                  <RelativePath>..\TouchGFX\Core\Inc\stm32f4xx_hal_conf.h</RelativePath>
                </VirtualFileSnapshot>
                <VirtualFileSnapshot>
                  <RelativePath>..\TouchGFX\Core\Inc\stm32f4xx_it.h</RelativePath>
                </VirtualFileSnapshot>
              </Files>
            </VirtualDirectorySnapshot>
            <VirtualDirectorySnapshot>
              <Name>STM32F4xx_HAL_Driver</Name>
              <Files>
                <VirtualFileSnapshot>
                  <RelativePath>..\TouchGFX\Drivers\STM32F4xx_HAL_Driver\Src\stm32f4xx_hal.c</RelativePath>
                </VirtualFileSnapshot>
                <VirtualFileSnapshot>
                  <RelativePath>..\TouchGFX\Drivers\STM32F4xx_HAL_Driver\Src\stm32f4xx_hal_cortex.c</RelativePath>
                </VirtualFileSnapshot>
                <VirtualFileSnapshot>
                  <RelativePath>..\TouchGFX\Drivers\STM32F4xx_HAL_Driver\Src\stm32f4xx_hal_crc.c</RelativePath>
                </VirtualFileSnapshot>
                <VirtualFileSnapshot>
                  <RelativePath>..\TouchGFX\Drivers\STM32F4xx_HAL_Driver\Src\stm32f4xx_hal_dma.c</RelativePath>
                </VirtualFileSnapshot>
                <VirtualFileSnapshot>
                  <RelativePath>..\TouchGFX\Drivers\STM32F4xx_HAL_Driver\Src\stm32f4xx_hal_dma2d.c</RelativePath>
                </VirtualFileSnapshot>
                <VirtualFileSnapshot>
                  <RelativePath>..\TouchGFX\Drivers\STM32F4xx_HAL_Driver\Src\stm32f4xx_hal_dma_ex.c</RelativePath>
                </VirtualFileSnapshot>
                <VirtualFileSnapshot>
                  <RelativePath>..\TouchGFX\Drivers\STM32F4xx_HAL_Driver\Src\stm32f4xx_hal_dsi.c</RelativePath>
                </VirtualFileSnapshot>
                <VirtualFileSnapshot>
                  <RelativePath>..\TouchGFX\Drivers\STM32F4xx_HAL_Driver\Src\stm32f4xx_hal_exti.c</RelativePath>
                </VirtualFileSnapshot>
                <VirtualFileSnapshot>
                  <RelativePath>..\TouchGFX\Drivers\STM32F4xx_HAL_Driver\Src\stm32f4xx_hal_flash.c</RelativePath>
                </VirtualFileSnapshot>
                <VirtualFileSnapshot>
                  <RelativePath>..\TouchGFX\Drivers\STM32F4xx_HAL_Driver\Src\stm32f4xx_hal_flash_ex.c</RelativePath>
                </VirtualFileSnapshot>
                <VirtualFileSnapshot>
                  <RelativePath>..\TouchGFX\Drivers\STM32F4xx_HAL_Driver\Src\stm32f4xx_hal_flash_ramfunc.c</RelativePath>
                </VirtualFileSnapshot>
                <VirtualFileSnapshot>
                  <RelativePath>..\TouchGFX\Drivers\STM32F4xx_HAL_Driver\Src\stm32f4xx_hal_gpio.c</RelativePath>
                </VirtualFileSnapshot>
                <VirtualFileSnapshot>
                  <RelativePath>..\TouchGFX\Drivers\STM32F4xx_HAL_Driver\Src\stm32f4xx_hal_i2c.c</RelativePath>
                </VirtualFileSnapshot>
                <VirtualFileSnapshot>
                  <RelativePath>..\TouchGFX\Drivers\STM32F4xx_HAL_Driver\Src\stm32f4xx_hal_i2c_ex.c</RelativePath>
                </VirtualFileSnapshot>
                <VirtualFileSnapshot>
                  <RelativePath>..\TouchGFX\Drivers\STM32F4xx_HAL_Driver\Src\stm32f4xx_hal_ltdc.c</RelativePath>
                </VirtualFileSnapshot>
                <VirtualFileSnapshot>
                  <RelativePath>..\TouchGFX\Drivers\STM32F4xx_HAL_Driver\Src\stm32f4xx_hal_ltdc_ex.c</RelativePath>
                </VirtualFileSnapshot>
                <VirtualFileSnapshot>
                  <RelativePath>..\TouchGFX\Drivers\STM32F4xx_HAL_Driver\Src\stm32f4xx_hal_pwr.c</RelativePath>
                </VirtualFileSnapshot>
                <VirtualFileSnapshot>
                  <RelativePath>..\TouchGFX\Drivers\STM32F4xx_HAL_Driver\Src\stm32f4xx_hal_pwr_ex.c</RelativePath>
                </VirtualFileSnapshot>
                <VirtualFileSnapshot>
                  <RelativePath>..\TouchGFX\Drivers\STM32F4xx_HAL_Driver\Src\stm32f4xx_hal_qspi.c</RelativePath>
                </VirtualFileSnapshot>
                <VirtualFileSnapshot>
                  <RelativePath>..\TouchGFX\Drivers\STM32F4xx_HAL_Driver\Src\stm32f4xx_hal_rcc.c</RelativePath>
                </VirtualFileSnapshot>
                <VirtualFileSnapshot>
                  <RelativePath>..\TouchGFX\Drivers\STM32F4xx_HAL_Driver\Src\stm32f4xx_hal_rcc_ex.c</RelativePath>
                </VirtualFileSnapshot>
                <VirtualFileSnapshot>
                  <RelativePath>..\TouchGFX\Drivers\STM32F4xx_HAL_Driver\Src\stm32f4xx_hal_sai.c</RelativePath>
                </VirtualFileSnapshot>
                <VirtualFileSnapshot>
                  <RelativePath>..\TouchGFX\Drivers\STM32F4xx_HAL_Driver\Src\stm32f4xx_hal_sai_ex.c</RelativePath>
                </VirtualFileSnapshot>
                <VirtualFileSnapshot>
                  <RelativePath>..\TouchGFX\Drivers\STM32F4xx_HAL_Driver\Src\stm32f4xx_hal_sd.c</RelativePath>
                </VirtualFileSnapshot>
                <VirtualFileSnapshot>
                  <RelativePath>..\TouchGFX\Drivers\STM32F4xx_HAL_Driver\Src\stm32f4xx_hal_sdram.c</RelativePath>
                </VirtualFileSnapshot>
                <VirtualFileSnapshot>
                  <RelativePath>..\TouchGFX\Drivers\STM32F4xx_HAL_Driver\Src\stm32f4xx_hal_tim.c</RelativePath>
                </VirtualFileSnapshot>
                <VirtualFileSnapshot>
                  <RelativePath>..\TouchGFX\Drivers\STM32F4xx_HAL_Driver\Src\stm32f4xx_hal_tim_ex.c</RelativePath>
                </VirtualFileSnapshot>
                <VirtualFileSnapshot>
                  <RelativePath>..\TouchGFX\Drivers\STM32F4xx_HAL_Driver\Src\stm32f4xx_hal_uart.c</RelativePath>
                </VirtualFileSnapshot>
                <VirtualFileSnapshot>
                  <RelativePath>..\TouchGFX\Drivers\STM32F4xx_HAL_Driver\Src\stm32f4xx_ll_fmc.c</RelativePath>
                </VirtualFileSnapshot>
                <VirtualFileSnapshot>
                  <RelativePath>..\TouchGFX\Drivers\STM32F4xx_HAL_Driver\Src\stm32f4xx_ll_sdmmc.c</RelativePath>
                </VirtualFileSnapshot>
                <VirtualFileSnapshot>
                  <RelativePath>..\TouchGFX\Drivers\STM32F4xx_HAL_Driver\Inc\stm32f4xx_hal.h</RelativePath>
                </VirtualFileSnapshot>
                <VirtualFileSnapshot>
                  <RelativePath>..\TouchGFX\Drivers\STM32F4xx_HAL_Driver\Inc\stm32f4xx_hal_cortex.h</RelativePath>
                </VirtualFileSnapshot>
                <VirtualFileSnapshot>
                  <RelativePath>..\TouchGFX\Drivers\STM32F4xx_HAL_Driver\Inc\stm32f4xx_hal_crc.h</RelativePath>
                </VirtualFileSnapshot>
                <VirtualFileSnapshot>
                  <RelativePath>..\TouchGFX\Drivers\STM32F4xx_HAL_Driver\Inc\stm32f4xx_hal_def.h</RelativePath>
                </VirtualFileSnapshot>
                <VirtualFileSnapshot>
                  <RelativePath>..\TouchGFX\Drivers\STM32F4xx_HAL_Driver\Inc\stm32f4xx_hal_dma.h</RelativePath>
                </VirtualFileSnapshot>
                <VirtualFileSnapshot>
                  <RelativePath>..\TouchGFX\Drivers\STM32F4xx_HAL_Driver\Inc\stm32f4xx_hal_dma2d.h</RelativePath>
                </VirtualFileSnapshot>
                <VirtualFileSnapshot>
                  <RelativePath>..\TouchGFX\Drivers\STM32F4xx_HAL_Driver\Inc\stm32f4xx_hal_dma_ex.h</RelativePath>
                </VirtualFileSnapshot>
                <VirtualFileSnapshot>
                  <RelativePath>..\TouchGFX\Drivers\STM32F4xx_HAL_Driver\Inc\stm32f4xx_hal_dsi.h</RelativePath>
                </VirtualFileSnapshot>
                <VirtualFileSnapshot>
                  <RelativePath>..\TouchGFX\Drivers\STM32F4xx_HAL_Driver\Inc\stm32f4xx_hal_exti.h</RelativePath>
                </VirtualFileSnapshot>
                <VirtualFileSnapshot>
                  <RelativePath>..\TouchGFX\Drivers\STM32F4xx_HAL_Driver\Inc\stm32f4xx_hal_flash.h</RelativePath>
                </VirtualFileSnapshot>
                <VirtualFileSnapshot>
                  <RelativePath>..\TouchGFX\Drivers\STM32F4xx_HAL_Driver\Inc\stm32f4xx_hal_flash_ex.h</RelativePath>
                </VirtualFileSnapshot>
                <VirtualFileSnapshot>
                  <RelativePath>..\TouchGFX\Drivers\STM32F4xx_HAL_Driver\Inc\stm32f4xx_hal_flash_ramfunc.h</RelativePath>
                </VirtualFileSnapshot>
                <VirtualFileSnapshot>
                  <RelativePath>..\TouchGFX\Drivers\STM32F4xx_HAL_Driver\Inc\stm32f4xx_hal_gpio.h</RelativePath>
                </VirtualFileSnapshot>
                <VirtualFileSnapshot>
                  <RelativePath>..\TouchGFX\Drivers\STM32F4xx_HAL_Driver\Inc\stm32f4xx_hal_gpio_ex.h</RelativePath>
                </VirtualFileSnapshot>
                <VirtualFileSnapshot>
                  <RelativePath>..\TouchGFX\Drivers\STM32F4xx_HAL_Driver\Inc\stm32f4xx_hal_i2c.h</RelativePath>
                </VirtualFileSnapshot>
                <VirtualFileSnapshot>
                  <RelativePath>..\TouchGFX\Drivers\STM32F4xx_HAL_Driver\Inc\stm32f4xx_hal_i2c_ex.h</RelativePath>
                </VirtualFileSnapshot>
                <VirtualFileSnapshot>
                  <RelativePath>..\TouchGFX\Drivers\STM32F4xx_HAL_Driver\Inc\stm32f4xx_hal_ltdc.h</RelativePath>
                </VirtualFileSnapshot>
                <VirtualFileSnapshot>
                  <RelativePath>..\TouchGFX\Drivers\STM32F4xx_HAL_Driver\Inc\stm32f4xx_hal_ltdc_ex.h</RelativePath>
                </VirtualFileSnapshot>
                <VirtualFileSnapshot>
                  <RelativePath>..\TouchGFX\Drivers\STM32F4xx_HAL_Driver\Inc\stm32f4xx_hal_pwr.h</RelativePath>
                </VirtualFileSnapshot>
                <VirtualFileSnapshot>
                  <RelativePath>..\TouchGFX\Drivers\STM32F4xx_HAL_Driver\Inc\stm32f4xx_hal_pwr_ex.h</RelativePath>
                </VirtualFileSnapshot>
                <VirtualFileSnapshot>
                  <RelativePath>..\TouchGFX\Drivers\STM32F4xx_HAL_Driver\Inc\stm32f4xx_hal_qspi.h</RelativePath>
                </VirtualFileSnapshot>
                <VirtualFileSnapshot>
                  <RelativePath>..\TouchGFX\Drivers\STM32F4xx_HAL_Driver\Inc\stm32f4xx_hal_rcc.h</RelativePath>
                </VirtualFileSnapshot>
                <VirtualFileSnapshot>
                  <RelativePath>..\TouchGFX\Drivers\STM32F4xx_HAL_Driver\Inc\stm32f4xx_hal_rcc_ex.h</RelativePath>
                </VirtualFileSnapshot>
                <VirtualFileSnapshot>
                  <RelativePath>..\TouchGFX\Drivers\STM32F4xx_HAL_Driver\Inc\stm32f4xx_hal_sai.h</RelativePath>
                </VirtualFileSnapshot>
                <VirtualFileSnapshot>
                  <RelativePath>..\TouchGFX\Drivers\STM32F4xx_HAL_Driver\Inc\stm32f4xx_hal_sai_ex.h</RelativePath>
                </VirtualFileSnapshot>
                <VirtualFileSnapshot>
                  <RelativePath>..\TouchGFX\Drivers\STM32F4xx_HAL_Driver\Inc\stm32f4xx_hal_sd.h</RelativePath>
                </VirtualFileSnapshot>
                <VirtualFileSnapshot>
                  <RelativePath>..\TouchGFX\Drivers\STM32F4xx_HAL_Driver\Inc\stm32f4xx_hal_sdram.h</RelativePath>
                </VirtualFileSnapshot>
                <VirtualFileSnapshot>
                  <RelativePath>..\TouchGFX\Drivers\STM32F4xx_HAL_Driver\Inc\stm32f4xx_hal_tim.h</RelativePath>
                </VirtualFileSnapshot>
                <VirtualFileSnapshot>
                  <RelativePath>..\TouchGFX\Drivers\STM32F4xx_HAL_Driver\Inc\stm32f4xx_hal_tim_ex.h</RelativePath>
                </VirtualFileSnapshot>
                <VirtualFileSnapshot>
                  <RelativePath>..\TouchGFX\Drivers\STM32F4xx_HAL_Driver\Inc\stm32f4xx_hal_uart.h</RelativePath>
                </VirtualFileSnapshot>
                <VirtualFileSnapshot>
                  <RelativePath>..\TouchGFX\Drivers\STM32F4xx_HAL_Driver\Inc\stm32f4xx_ll_fmc.h</RelativePath>
                </VirtualFileSnapshot>
                <VirtualFileSnapshot>
                  <RelativePath>..\TouchGFX\Drivers\STM32F4xx_HAL_Driver\Inc\stm32f4xx_ll_sdmmc.h</RelativePath>
                </VirtualFileSnapshot>
              </Files>
            </VirtualDirectorySnapshot>
            <VirtualDirectorySnapshot>
              <Name>BSP</Name>
              <Subdirectories>
                <VirtualDirectorySnapshot>
                  <Name>Components</Name>
                  <Files>
                    <VirtualFileSnapshot>
                      <RelativePath>..\TouchGFX\Drivers\BSP\Components\ft6x06\ft6x06.c</RelativePath>
                    </VirtualFileSnapshot>
                    <VirtualFileSnapshot>
                      <RelativePath>..\TouchGFX\Drivers\BSP\Components\otm8009a\otm8009a.c</RelativePath>
                    </VirtualFileSnapshot>
                  </Files>
                </VirtualDirectorySnapshot>
                <VirtualDirectorySnapshot>
                  <Name>STM32469I-Discovery</Name>
                  <Files>
                    <VirtualFileSnapshot>
                      <RelativePath>..\TouchGFX\Drivers\BSP\STM32469I-Discovery\stm32469i_discovery.c</RelativePath>
                    </VirtualFileSnapshot>
                    <VirtualFileSnapshot>
                      <RelativePath>..\TouchGFX\Drivers\BSP\STM32469I-Discovery\stm32469i_discovery_qspi.c</RelativePath>
                    </VirtualFileSnapshot>
                    <VirtualFileSnapshot>
                      <RelativePath>..\TouchGFX\Drivers\BSP\STM32469I-Discovery\stm32469i_discovery_sdram.c</RelativePath>
                    </VirtualFileSnapshot>
                    <VirtualFileSnapshot>
                      <RelativePath>..\TouchGFX\Drivers\BSP\STM32469I-Discovery\stm32469i_discovery_ts.c</RelativePath>
                    </VirtualFileSnapshot>
                  </Files>
                </VirtualDirectorySnapshot>
              </Subdirectories>
              <Files />
            </VirtualDirectorySnapshot>
          </Subdirectories>
          <Files />
        </VirtualDirectorySnapshot>
        <VirtualDirectorySnapshot>
          <Name>Middlewares</Name>
          <Subdirectories>
            <VirtualDirectorySnapshot>
              <Name>FreeRTOS</Name>
              <Files>
                <VirtualFileSnapshot>
                  <RelativePath>..\TouchGFX\Middlewares\Third_Party\FreeRTOS\Source\CMSIS_RTOS_V2\cmsis_os2.c</RelativePath>
                </VirtualFileSnapshot>
                <VirtualFileSnapshot>
                  <RelativePath>..\TouchGFX\Middlewares\Third_Party\FreeRTOS\Source\croutine.c</RelativePath>
                </VirtualFileSnapshot>
                <VirtualFileSnapshot>
                  <RelativePath>..\TouchGFX\Middlewares\Third_Party\FreeRTOS\Source\event_groups.c</RelativePath>
                </VirtualFileSnapshot>
                <VirtualFileSnapshot>
                  <RelativePath>..\TouchGFX\Middlewares\Third_Party\FreeRTOS\Source\portable\MemMang\heap_4.c</RelativePath>
                </VirtualFileSnapshot>
                <VirtualFileSnapshot>
                  <RelativePath>..\TouchGFX\Middlewares\Third_Party\FreeRTOS\Source\list.c</RelativePath>
                </VirtualFileSnapshot>
                <VirtualFileSnapshot>
                  <RelativePath>..\TouchGFX\Middlewares\Third_Party\FreeRTOS\Source\portable\GCC\ARM_CM4F\port.c</RelativePath>
                </VirtualFileSnapshot>
                <VirtualFileSnapshot>
                  <RelativePath>..\TouchGFX\Middlewares\Third_Party\FreeRTOS\Source\queue.c</RelativePath>
                </VirtualFileSnapshot>
                <VirtualFileSnapshot>
                  <RelativePath>..\TouchGFX\Middlewares\Third_Party\FreeRTOS\Source\stream_buffer.c</RelativePath>
                </VirtualFileSnapshot>
                <VirtualFileSnapshot>
                  <RelativePath>..\TouchGFX\Middlewares\Third_Party\FreeRTOS\Source\tasks.c</RelativePath>
                </VirtualFileSnapshot>
                <VirtualFileSnapshot>
                  <RelativePath>..\TouchGFX\Middlewares\Third_Party\FreeRTOS\Source\timers.c</RelativePath>
                </VirtualFileSnapshot>
              </Files>
            </VirtualDirectorySnapshot>
          </Subdirectories>
          <Files />
        </VirtualDirectorySnapshot>
      </Subdirectories>
      <Files>
        <VirtualFileSnapshot>
          <RelativePath>..\TouchGFX\Drivers\STM32F4xx_HAL_Driver\Inc\Legacy\stm32_hal_legacy.h</RelativePath>
        </VirtualFileSnapshot>
      </Files>
    </RootDirectory>
    <Configurations>
      <ImportedConfiguration>
        <IsStaticLibrary>false</IsStaticLibrary>
        <Settings>
          <IncludeDirectories>
            <string>D:\Projects\DCC\STM32F469_Controller\Source\TouchGFX\Core\Inc</string>
            <string>D:\Projects\DCC\STM32F469_Controller\Source\TouchGFX\Drivers\CMSIS\Include</string>
            <string>D:\Projects\DCC\STM32F469_Controller\Source\TouchGFX\TouchGFX\generated\gui_generated\include</string>
            <string>D:\Projects\DCC\STM32F469_Controller\Source\TouchGFX\TouchGFX\target</string>
            <string>D:\Projects\DCC\STM32F469_Controller\Source\TouchGFX\Drivers\CMSIS\Device\ST\STM32F4xx\Include</string>
            <string>D:\Projects\DCC\STM32F469_Controller\Source\TouchGFX\TouchGFX\App</string>
            <string>D:\Projects\DCC\STM32F469_Controller\Source\TouchGFX\Middlewares\ST\touchgfx\framework\include</string>
            <string>D:\Projects\DCC\STM32F469_Controller\Source\TouchGFX\Middlewares\Third_Party\FreeRTOS\Source\CMSIS_RTOS_V2</string>
            <string>D:\Projects\DCC\STM32F469_Controller\Source\TouchGFX\TouchGFX\target\generated</string>
            <string>D:\Projects\DCC\STM32F469_Controller\Source\TouchGFX\Drivers\BSP\Components\Common</string>
            <string>D:\Projects\DCC\STM32F469_Controller\Source\TouchGFX\TouchGFX\gui\include</string>
            <string>D:\Projects\DCC\STM32F469_Controller\Source\TouchGFX\TouchGFX\generated\texts\include</string>
            <string>D:\Projects\DCC\STM32F469_Controller\Source\TouchGFX\TouchGFX\generated\images\include</string>
            <string>D:\Projects\DCC\STM32F469_Controller\Source\TouchGFX\Middlewares\Third_Party\FreeRTOS\Source\include</string>
            <string>D:\Projects\DCC\STM32F469_Controller\Source\TouchGFX\Drivers\STM32F4xx_HAL_Driver\Inc\Legacy</string>
            <string>D:\Projects\DCC\STM32F469_Controller\Source\TouchGFX\Middlewares\Third_Party\FreeRTOS\Source\portable\GCC\ARM_CM4F</string>
            <string>D:\Projects\DCC\STM32F469_Controller\Source\TouchGFX\Drivers\BSP\STM32469I-Discovery</string>
            <string>D:\Projects\DCC\STM32F469_Controller\Source\TouchGFX\TouchGFX\generated\fonts\include</string>
            <string>D:\Projects\DCC\STM32F469_Controller\Source\TouchGFX\Drivers\STM32F4xx_HAL_Driver\Inc</string>
          </IncludeDirectories>
          <PreprocessorMacros>
            <string>USE_HAL_DRIVER</string>
            <string>STM32F469xx</string>
          </PreprocessorMacros>
          <GeneratePreprocessorOutput>false</GeneratePreprocessorOutput>
          <IsDebugConfiguration>false</IsDebugConfiguration>
        </Settings>
      </ImportedConfiguration>
    </Configurations>
  </ImportedProject>
</EmbeddedProfile>